league_tools/__init__.py
league_tools/core/__init__.py
league_tools/core/binary.py
league_tools/core/exceptions.py
league_tools/core/section.py
league_tools/formats/__init__.py
league_tools/formats/bin/__init__.py
league_tools/formats/bin/constants.py
league_tools/formats/bin/models.py
league_tools/formats/bin/parser.py
league_tools/formats/bnk/__init__.py
league_tools/formats/bnk/parser.py
league_tools/formats/bnk/wwiser.py
league_tools/formats/bnk/section/BKHD.py
league_tools/formats/bnk/section/DATA.py
league_tools/formats/bnk/section/DIDX.py
league_tools/formats/bnk/section/HIRC.py
league_tools/formats/bnk/section/_HIRC.py
league_tools/formats/bnk/section/__init__.py
league_tools/formats/wad/__init__.py
league_tools/formats/wad/parser.py
league_tools/formats/wpk/__init__.py
league_tools/formats/wpk/parser.py
league_tools/utils/__init__.py
league_tools/utils/hash.py
league_tools/utils/type_hints.py
league_tools/utils/wwiser.py
league_tools/utils/xml.py
league_tools-1.1.0.dist-info/METADATA
league_tools-1.1.0.dist-info/WHEEL
league_tools-1.1.0.dist-info/licenses/LICENSE
league_tools-1.1.0.dist-info/RECORD
