Metadata-Version: 2.4
Name: league-tools
Version: 1.1.0
Summary: WAD、BIN、BNK、WPK文件简单处理
Project-URL: homepage, https://github.com/Virace/py-bnk-extract
Project-URL: repository, https://github.com/Virace/py-bnk-extract
Project-URL: Bug Tracker, https://github.com/Virace/py-bnk-extract/issues
Author-email: Virace <Virace@aliyun.com>
License:                     GNU GENERAL PUBLIC LICENSE
License-File: LICENSE
Keywords: bnk,league,wad
Classifier: Development Status :: 5 - Production/Stable
Classifier: License :: OSI Approved :: GNU General Public License v3 (GPLv3)
Classifier: Operating System :: OS Independent
Classifier: Programming Language :: Python
Classifier: Programming Language :: Python :: 3
Classifier: Programming Language :: Python :: 3 :: Only
Classifier: Programming Language :: Python :: 3.10
Requires-Python: >=3.10
Requires-Dist: loguru>=0.7.2
Requires-Dist: lxml>=5.4.0
Requires-Dist: quick-xmltodict>=0.1.3
Requires-Dist: requests>=2.32.3
Requires-Dist: xxhash>=3.4.1
Requires-Dist: zstd>=1.5.5.1
